django_template_admin-2.1.0.dist-info/licenses/LICENSE
template_admin/__init__.py
template_admin/admin.py
template_admin/apps.py
template_admin/loader.py
template_admin/models.py
template_admin/locale/cs/LC_MESSAGES/django.mo
template_admin/locale/cs/LC_MESSAGES/django.po
template_admin/migrations/0001_initial.py
template_admin/migrations/__init__.py
template_admin/static/template_admin/htmldiff.css
tests/__init__.py
tests/settings.py
tests/tests.py
tests/urls.py
django_template_admin-2.1.0.dist-info/METADATA
django_template_admin-2.1.0.dist-info/WHEEL
django_template_admin-2.1.0.dist-info/top_level.txt
django_template_admin-2.1.0.dist-info/RECORD
